setup.py
chimpy/README.txt
chimpy/__init__.py
chimpy/chimpy.py
chimpy/test_chimpy.py
chimpy/utils.py
chimpy/v12.py
chimpy.egg-info/PKG-INFO
chimpy.egg-info/SOURCES.txt
chimpy.egg-info/dependency_links.txt
chimpy.egg-info/not-zip-safe
chimpy.egg-info/requires.txt
chimpy.egg-info/top_level.txt