Metadata-Version: 1.0
Name: chimpy
Version: 0.2b2
Summary: Python wrapper for the MailChimp API
Home-page: http://code.google.com/p/chimpy/
Author: James Casbon, Anton Stonor
Author-email: casbon@gmail.com
License: New BSD License
Keywords: email mail mailinglist newsletter
Platform: UNKNOWN
Classifier: Environment :: Web Environment
Classifier: Intended Audience :: Developers
Classifier: License :: OSI Approved :: BSD License
Classifier: Operating System :: OS Independent
Classifier: Programming Language :: Python
Classifier: Topic :: Software Development :: Libraries :: Python Modules
